yumlib/__init__.py
yumlib/main.py
yumlib-0.1.4.8.8.dist-info/LICENSE.md
yumlib-0.1.4.8.8.dist-info/METADATA
yumlib-0.1.4.8.8.dist-info/WHEEL
yumlib-0.1.4.8.8.dist-info/top_level.txt
yumlib-0.1.4.8.8.dist-info/RECORD
