Metadata-Version: 2.1
Name: yumlib
Version: 0.1.4.8.8
Summary: testekk
Home-page: https://ямме.рф
Author: yummy1gay
Author-email: yummy@gmail.com
License: MIT
Platform: UNKNOWN
Classifier: Programming Language :: Python :: 3
Classifier: License :: OSI Approved :: MIT License
Classifier: Operating System :: OS Independent
Requires-Python: >=3.6
License-File: LICENSE.md
Requires-Dist: Telethon
